pynanoflann/nanoflann.py
pynanoflann/__init__.py
pynanoflann/nanoflann_ext.pypy39-pp73-darwin.so
pynanoflann-0.10.0.dist-info/RECORD
pynanoflann-0.10.0.dist-info/WHEEL
pynanoflann-0.10.0.dist-info/METADATA
pynanoflann-0.10.0.dist-info/licenses/LICENSE
